square/__init__.py
square/__main__.py
Narsi_square-1.0.1.dist-info/LICENSE
Narsi_square-1.0.1.dist-info/METADATA
Narsi_square-1.0.1.dist-info/WHEEL
Narsi_square-1.0.1.dist-info/entry_points.txt
Narsi_square-1.0.1.dist-info/top_level.txt
Narsi_square-1.0.1.dist-info/RECORD
