Metadata-Version: 2.1
Name: Narsi-square
Version: 1.0.1
Summary: It squares the number
Home-page: https://github.com/Narasimha-sai/Narsi-square
Author: Narasimha Sai
Author-email: mymail@mail.com
License: MIT
Platform: UNKNOWN
Classifier: License :: OSI Approved :: MIT License
Classifier: Programming Language :: Python :: 3.6
Classifier: Programming Language :: Python :: 3.7
Classifier: Programming Language :: Python :: 3.8
